<?xml version="1.0" encoding="utf-8" ?>
		<hibernate-mapping xmlns="urn:nhibernate-mapping-2.2"
		                   assembly="IManagerGenNHibernate"
		                   namespace="IManagerGenNHibernate.EN.IManager">
		    
		    
			
				<class name="AparienciaEN" table="Apariencia"> 
						<id name="Nombre" column="nombre"/> 
			
					
					<property name="Logo" type="string"> 
						<column name="logo"  not-null="true"/>
					</property>
					<property name="SuperAdmin" type="string"> 
						<column name="superAdmin"  not-null="true"/>
					</property>
					<property name="Admin" type="string"> 
						<column name="admin"  not-null="true"/>
					</property>
					<property name="Empleado" type="string"> 
						<column name="empleado"  not-null="true"/>
					</property>
			
			
			
			
			
			
					
					
					
					
					
		
		 </class>	
		  
		  <query name="AparienciaENReadAllHQL">from AparienciaEN</query>
		</hibernate-mapping>
	